{
  "updated_at": "2026-04-22T17:04:26Z",
  "items": [
    {
      "id": "feed_20260423_020426",
      "kind": "event",
      "date": "2026-04-23",
      "created_at": "2026-04-22T17:04:26Z",
      "text": "うんこが出たので、トイレに向かいに行かざるを得なかった。",
      "tweet": "うんこが出たので、トイレに向かいに行かざるを得なかった。",
      "place": "",
      "links": [],
      "avatar_image": "image/avatar/normal.png",
      "permalink": "./?post=feed_20260423_020426",
      "legacy_id": "fixed-event-20260423_020426",
      "image": "image/feed_20260423_020426.png",
      "image_url": "image/feed_20260423_020426.png",
      "avatar_url": "image/avatar/normal.png",
      "image_prompt": "illustration, clear composition, soft lighting, suitable for an event post, scene in Yokosuka, Japan. Inspired by: うんこが出たので、トイレに向かいに行かざるを得なかった。",
      "image_negative": "photorealistic, text, watermark, logo, low quality, blurry, underexposed, too dark",
      "image_model": "stabilityai/sdxl-turbo",
      "image_generated_at": "2026-04-22T17:08:59Z"
    }
  ]
}
